{
  "ops": [
    {
      "kind": "UpdateFile",
      "path": "/rootfs/etc/passwd",
      "content": [
        52,
        137,
        5,
        44,
        146,
        169,
        124,
        247,
        0,
        87,
        200,
        61,
        191,
        3,
        220,
        248,
        81,
        194,
        1,
        6,
        106,
        162,
        221,
        63,
        191,
        225,
        142,
        216,
        54,
        170,
        181,
        18,
        20,
        186,
        202,
        91,
        215,
        190,
        228
      ],
      "size": 39,
      "mtime_sec": 0,
      "mtime_nsec": 0,
      "atime_sec": 0,
      "atime_nsec": 0
    },
    {
      "kind": "CreateFile",
      "path": "/lib/tmp",
      "content": [
        207,
        177,
        132,
        103,
        236,
        122,
        52,
        113,
        25,
        161,
        37,
        132,
        73,
        24,
        61,
        145,
        110,
        17,
        159,
        188,
        139,
        157,
        16,
        77,
        37,
        47,
        141,
        107,
        248
      ],
      "size": 29,
      "mtime_sec": 0,
      "mtime_nsec": 0,
      "atime_sec": 0,
      "atime_nsec": 0
    },
    {
      "kind": "UpdateFile",
      "path": "/rootfs/etc/hosts",
      "content": [
        56,
        60,
        162,
        6,
        189,
        196,
        146,
        229,
        163,
        114,
        50,
        29,
        145,
        83,
        222,
        177,
        242,
        101,
        63,
        154,
        123,
        228,
        79,
        91,
        180,
        191,
        173,
        141,
        4,
        16,
        147,
        56,
        241,
        81,
        116,
        218,
        235,
        254,
        61,
        49,
        108,
        74,
        176,
        70,
        192,
        221,
        14,
        106,
        139,
        236,
        176,
        145,
        211,
        128,
        253,
        103,
        21,
        11,
        36
      ],
      "size": 59,
      "mtime_sec": 0,
      "mtime_nsec": 0,
      "atime_sec": 0,
      "atime_nsec": 0
    },
    {
      "kind": "SetTimes",
      "path": "/rootfs/etc",
      "content": [],
      "size": 0,
      "mtime_sec": 3456574055,
      "mtime_nsec": 0,
      "atime_sec": 2000000000,
      "atime_nsec": 0
    },
    {
      "kind": "Rmdir",
      "path": "/rootfs/run",
      "content": [],
      "size": 0,
      "mtime_sec": 0,
      "mtime_nsec": 0,
      "atime_sec": 0,
      "atime_nsec": 0
    },
    {
      "kind": "CreateFile",
      "path": "/test/lib/input",
      "content": [
        204,
        63,
        68,
        136
      ],
      "size": 4,
      "mtime_sec": 0,
      "mtime_nsec": 0,
      "atime_sec": 0,
      "atime_nsec": 0
    },
    {
      "kind": "Rmdir",
      "path": "/tmp/usr",
      "content": [],
      "size": 0,
      "mtime_sec": 0,
      "mtime_nsec": 0,
      "atime_sec": 0,
      "atime_nsec": 0
    },
    {
      "kind": "UpdateFile",
      "path": "/rootfs/etc/hostname",
      "content": [
        2,
        82,
        147,
        10,
        86,
        187,
        54,
        193,
        112,
        230,
        87,
        212,
        174,
        59,
        138,
        178,
        147,
        192,
        251,
        196,
        247,
        224,
        96,
        60
      ],
      "size": 24,
      "mtime_sec": 0,
      "mtime_nsec": 0,
      "atime_sec": 0,
      "atime_nsec": 0
    },
    {
      "kind": "Mkdir",
      "path": "/lib/a",
      "content": [],
      "size": 0,
      "mtime_sec": 0,
      "mtime_nsec": 0,
      "atime_sec": 0,
      "atime_nsec": 0
    },
    {
      "kind": "Rmdir",
      "path": "/rootfs/dev",
      "content": [],
      "size": 0,
      "mtime_sec": 0,
      "mtime_nsec": 0,
      "atime_sec": 0,
      "atime_nsec": 0
    },
    {
      "kind": "CreateFile",
      "path": "/data",
      "content": [
        32,
        123,
        199,
        153,
        129,
        66,
        172,
        39,
        153,
        94,
        11,
        150,
        149,
        119,
        113,
        104,
        64,
        50,
        242,
        14,
        53,
        73,
        182,
        173,
        193,
        93,
        168,
        183,
        58,
        1,
        7,
        185,
        110,
        27
      ],
      "size": 34,
      "mtime_sec": 0,
      "mtime_nsec": 0,
      "atime_sec": 0,
      "atime_nsec": 0
    },
    {
      "kind": "UpdateFile",
      "path": "/rootfs/bin/true",
      "content": [
        150,
        121,
        251,
        150,
        140,
        39,
        123,
        45,
        132,
        181,
        45,
        19,
        96,
        9,
        193,
        191,
        237,
        87,
        68,
        49,
        190,
        243,
        65,
        101,
        66,
        38,
        208,
        50,
        76,
        86,
        92,
        184,
        192,
        234,
        98,
        60,
        86,
        97,
        78,
        163,
        211,
        243,
        21,
        121,
        181,
        98,
        136,
        25
      ],
      "size": 48,
      "mtime_sec": 0,
      "mtime_nsec": 0,
      "atime_sec": 0,
      "atime_nsec": 0
    },
    {
      "kind": "CreateFile",
      "path": "/c",
      "content": [
        68,
        117,
        183,
        210,
        75,
        166,
        74,
        39,
        251,
        9,
        3,
        136,
        41,
        78,
        213,
        107,
        244,
        178,
        93,
        48,
        243,
        194,
        83,
        243,
        144,
        228,
        189,
        193,
        125,
        46,
        21,
        96,
        40,
        24,
        181,
        151,
        62,
        55,
        20,
        125,
        64,
        21,
        133,
        116,
        219,
        200,
        49,
        178,
        111,
        247,
        64,
        76,
        207,
        90,
        131,
        60,
        184,
        212,
        121
      ],
      "size": 59,
      "mtime_sec": 0,
      "mtime_nsec": 0,
      "atime_sec": 0,
      "atime_nsec": 0
    },
    {
      "kind": "DeleteFile",
      "path": "/config/lib/a",
      "content": [],
      "size": 0,
      "mtime_sec": 0,
      "mtime_nsec": 0,
      "atime_sec": 0,
      "atime_nsec": 0
    },
    {
      "kind": "UpdateFile",
      "path": "/config.json",
      "content": [
        123,
        34,
        104,
        111,
        115,
        116,
        110,
        97,
        109,
        101,
        34,
        58,
        34,
        102,
        117,
        122,
        122,
        34,
        44,
        34,
        108,
        105,
        110,
        117,
        120,
        34,
        58,
        123,
        34,
        103,
        105,
        100,
        77,
        97,
        112,
        112,
        105,
        110,
        103,
        115,
        34,
        58,
        91,
        123,
        34,
        99,
        111,
        110,
        116,
        97,
        105,
        110,
        101,
        114,
        73,
        68,
        34,
        58,
        48,
        44,
        34,
        104,
        111,
        115,
        116,
        73,
        68,
        34,
        58,
        49,
        48,
        48,
        51,
        44,
        34,
        115,
        105,
        122,
        101,
        34,
        58,
        49,
        125,
        93,
        44,
        34,
        110,
        97,
        109,
        101,
        115,
        112,
        97,
        99,
        101,
        115,
        34,
        58,
        91,
        123,
        34,
        116,
        121,
        112,
        101,
        34,
        58,
        34,
        112,
        105,
        100,
        34,
        125,
        44,
        123,
        34,
        116,
        121,
        112,
        101,
        34,
        58,
        34,
        109,
        111,
        117,
        110,
        116,
        34,
        125,
        44,
        123,
        34,
        116,
        121,
        112,
        101,
        34,
        58,
        34,
        117,
        115,
        101,
        114,
        34,
        125,
        93,
        44,
        34,
        117,
        105,
        100,
        77,
        97,
        112,
        112,
        105,
        110,
        103,
        115,
        34,
        58,
        91,
        123,
        34,
        99,
        111,
        110,
        116,
        97,
        105,
        110,
        101,
        114,
        73,
        68,
        34,
        58,
        48,
        44,
        34,
        106,
        111,
        115,
        116,
        73,
        68,
        34,
        58,
        49,
        48,
        48,
        51,
        44,
        34,
        115,
        105,
        122,
        101,
        34,
        58,
        49,
        125,
        93,
        125,
        44,
        34,
        111,
        99,
        105,
        86,
        101,
        114,
        115,
        105,
        111,
        110,
        34,
        58,
        34,
        49,
        46,
        48,
        46,
        48,
        34,
        44,
        34,
        112,
        114,
        111,
        99,
        101,
        115,
        115,
        34,
        58,
        123,
        34,
        97,
        114,
        103,
        115,
        34,
        58,
        91,
        34,
        47,
        98,
        105,
        110,
        47,
        116,
        114,
        117,
        101,
        34,
        93,
        44,
        34,
        99,
        119,
        100,
        34,
        58,
        34,
        47,
        34,
        44,
        34,
        101,
        110,
        118,
        34,
        58,
        91,
        34,
        80,
        65,
        84,
        72,
        61,
        47,
        117,
        115,
        114,
        47,
        108,
        111,
        99,
        97,
        108,
        47,
        115,
        98,
        105,
        110,
        58,
        47,
        117,
        115,
        114,
        47,
        108,
        111,
        99,
        97,
        108,
        47,
        98,
        105,
        110,
        58,
        47,
        117,
        115,
        114,
        47,
        115,
        98,
        105,
        110,
        58,
        47,
        117,
        115,
        114,
        47,
        98,
        105,
        110,
        58,
        47,
        115,
        98,
        105,
        110,
        58,
        47,
        98,
        105,
        110,
        34,
        93,
        44,
        34,
        110,
        111,
        78,
        101,
        119,
        80,
        114,
        105,
        118,
        105,
        108,
        101,
        103,
        101,
        115,
        34,
        58,
        116,
        114,
        117,
        101,
        44,
        34,
        116,
        101,
        114,
        109,
        105,
        110,
        97,
        108,
        34,
        58,
        102,
        97,
        108,
        115,
        101,
        44,
        34,
        117,
        115,
        103,
        114,
        34,
        58,
        123,
        34,
        103,
        105,
        100,
        34,
        58,
        48,
        44,
        34,
        117,
        105,
        100,
        34,
        58,
        48,
        125,
        125,
        44,
        34,
        114,
        111,
        111,
        116,
        34,
        58,
        123,
        34,
        112,
        97,
        116,
        104,
        34,
        58,
        34,
        47,
        116,
        109,
        112,
        47,
        109,
        112,
        105,
        45,
        115,
        112,
        45,
        102,
        117,
        115,
        101,
        45,
        99,
        114,
        117,
        110,
        45,
        49,
        51,
        54,
        56,
        53,
        55,
        54,
        47,
        114,
        111,
        111,
        116,
        102,
        115,
        34,
        44,
        34,
        114,
        101,
        97,
        100,
        111,
        110,
        108,
        121,
        34,
        58,
        102,
        97,
        108,
        115,
        101,
        125,
        125
      ],
      "size": 483,
      "mtime_sec": 0,
      "mtime_nsec": 0,
      "atime_sec": 0,
      "atime_nsec": 0
    },
    {
      "kind": "Rmdir",
      "path": "/rootfs/sys",
      "content": [],
      "size": 0,
      "mtime_sec": 0,
      "mtime_nsec": 0,
      "atime_sec": 0,
      "atime_nsec": 0
    },
    {
      "kind": "SetTimes",
      "path": "/lib/a/config",
      "content": [],
      "size": 0,
      "mtime_sec": 1321059529,
      "mtime_nsec": 0,
      "atime_sec": 0,
      "atime_nsec": 0
    },
    {
      "kind": "Rmdir",
      "path": "/rootfs/bin",
      "content": [],
      "size": 0,
      "mtime_sec": 0,
      "mtime_nsec": 0,
      "atime_sec": 0,
      "atime_nsec": 0
    },
    {
      "kind": "Mkdir",
      "path": "/input/c",
      "content": [],
      "size": 0,
      "mtime_sec": 0,
      "mtime_nsec": 0,
      "atime_sec": 0,
      "atime_nsec": 0
    }
  ]
}